cloud_tpu_profiler/__init__.py
cloud_tpu_profiler/capture_tpu_profile.py
cloud_tpu_profiler/version.py
cloud_tpu_profiler-2.4.0.dist-info/METADATA
cloud_tpu_profiler-2.4.0.dist-info/WHEEL
cloud_tpu_profiler-2.4.0.dist-info/entry_points.txt
cloud_tpu_profiler-2.4.0.dist-info/top_level.txt
cloud_tpu_profiler-2.4.0.dist-info/RECORD
